<?xml version="1.0" encoding="UTF-8"?>
<!DOCTYPE struts PUBLIC
    "-//Apache Software Foundation//DTD Struts Configuration 2.0//EN"
    "http://struts.apache.org/dtds/struts-2.0.dtd">

<struts>

	<package name="mock" extends="rap-default" namespace="/mock">

		<action name="modify" class="com.taobao.rigel.rap.mock.web.action.MockAction"
			method="modify">
			<result name="success" type="velocity">/bcom/isOkWithNum.cb.vm
			</result>
		</action>

		<action name="reset" class="com.taobao.rigel.rap.mock.web.action.MockAction"
			method="reset">
			<result name="success" type="velocity">/bcom/isOkWithNum.cb.vm
			</result>
		</action>

		<action name="createData" class="com.taobao.rigel.rap.mock.web.action.MockAction"
			method="createData">
			<result name="error" type="velocity">/bcom/contentWithoutEscape.cb.vm
			</result>
			<result name="success" type="velocity">/bcom/contentWithoutEscape.cb.vm
			</result>
		</action>
		
		<action name="createRule" class="com.taobao.rigel.rap.mock.web.action.MockAction"
			method="createRule">
			<result name="error" type="velocity">/bcom/contentWithoutEscape.cb.vm
			</result>
			<result name="success" type="velocity">/bcom/contentWithoutEscape.cb.vm
			</result>

		</action>

	</package>
</struts>